django_bower-5.1.0.dist-info/DESCRIPTION.rst
django_bower-5.1.0.dist-info/METADATA
django_bower-5.1.0.dist-info/RECORD
django_bower-5.1.0.dist-info/WHEEL
django_bower-5.1.0.dist-info/entry_points.txt
django_bower-5.1.0.dist-info/metadata.json
django_bower-5.1.0.dist-info/top_level.txt
django_bower-5.1.0.dist-info/zip-safe
djangobower/__init__.py
djangobower/bower.py
djangobower/conf.py
djangobower/context_processors.py
djangobower/exceptions.py
djangobower/finders.py
djangobower/models.py
djangobower/shortcuts.py
djangobower/test_settings.py
djangobower/management/__init__.py
djangobower/management/base.py
djangobower/management/commands/__init__.py
djangobower/management/commands/bower.py
djangobower/management/commands/bower_freeze.py
djangobower/management/commands/bower_install.py
djangobower/templatetags/__init__.py
djangobower/templatetags/bower.py
djangobower/tests/__init__.py
djangobower/tests/base.py
djangobower/tests/test_bower.py
djangobower/tests/test_finders.py
