Metadata-Version: 1.1
Name: django-bower
Version: 5.1.0
Summary: Integrate django with bower
Home-page: https://github.com/nvbn/django-bower
Author: Vladimir Iakovlev
Author-email: nvbn.rm@gmail.com
License: BSD
Platform: UNKNOWN
Classifier: Framework :: Django
Classifier: Programming Language :: JavaScript
Classifier: Programming Language :: Python
Classifier: Programming Language :: Python :: 3
